easypaddleocr/__init__.py
easypaddleocr/base_ocr_v20.py
easypaddleocr/config.py
easypaddleocr/predict_cls.py
easypaddleocr/predict_det.py
easypaddleocr/predict_rec.py
easypaddleocr/predict_system.py
easypaddleocr/pytorchocr_utility.py
easypaddleocr/pytorchocr/__init__.py
easypaddleocr/pytorchocr/data/__init__.py
easypaddleocr/pytorchocr/data/imaug/__init__.py
easypaddleocr/pytorchocr/data/imaug/gen_table_mask.py
easypaddleocr/pytorchocr/data/imaug/operators.py
easypaddleocr/pytorchocr/modeling/__init__.py
easypaddleocr/pytorchocr/modeling/common.py
easypaddleocr/pytorchocr/modeling/architectures/__init__.py
easypaddleocr/pytorchocr/modeling/architectures/base_model.py
easypaddleocr/pytorchocr/modeling/backbones/__init__.py
easypaddleocr/pytorchocr/modeling/backbones/det_mobilenet_v3.py
easypaddleocr/pytorchocr/modeling/backbones/det_resnet.py
easypaddleocr/pytorchocr/modeling/backbones/det_resnet_vd.py
easypaddleocr/pytorchocr/modeling/backbones/det_resnet_vd_sast.py
easypaddleocr/pytorchocr/modeling/backbones/e2e_resnet_vd_pg.py
easypaddleocr/pytorchocr/modeling/backbones/rec_densenet.py
easypaddleocr/pytorchocr/modeling/backbones/rec_hgnet.py
easypaddleocr/pytorchocr/modeling/backbones/rec_lcnetv3.py
easypaddleocr/pytorchocr/modeling/backbones/rec_lcnetv3_bak.py
easypaddleocr/pytorchocr/modeling/backbones/rec_mobilenet_v3.py
easypaddleocr/pytorchocr/modeling/backbones/rec_mv1_enhance.py
easypaddleocr/pytorchocr/modeling/backbones/rec_nrtr_mtb.py
easypaddleocr/pytorchocr/modeling/backbones/rec_resnet_31.py
easypaddleocr/pytorchocr/modeling/backbones/rec_resnet_fpn.py
easypaddleocr/pytorchocr/modeling/backbones/rec_resnet_vd.py
easypaddleocr/pytorchocr/modeling/backbones/rec_svtrnet.py
easypaddleocr/pytorchocr/modeling/backbones/rec_vitstr.py
easypaddleocr/pytorchocr/modeling/backbones/table_mobilenet_v3.py
easypaddleocr/pytorchocr/modeling/backbones/table_resnet_vd.py
easypaddleocr/pytorchocr/modeling/heads/__init__.py
easypaddleocr-0.3.dist-info/METADATA
easypaddleocr-0.3.dist-info/WHEEL
easypaddleocr-0.3.dist-info/licenses/LICENSE
easypaddleocr-0.3.dist-info/RECORD
