Metadata-Version: 2.2
Name: easypaddleocr
Version: 0.3
Summary: A simple, optional tool for PaddleOCR Detection, direction classification and recognition on CPU and GPU using torch.
Author: pk5ls20, hv0905
Project-URL: Code, https://github.com/pk5ls20/EasyPaddleOCR
Project-URL: Documentation, https://github.com/pk5ls20/EasyPaddleOCR
Project-URL: Download, https://pypi.org/project/easypaddleocr
Project-URL: Homepage, https://github.com/pk5ls20/EasyPaddleOCR
Project-URL: Issues, https://github.com/pk5ls20/EasyPaddleOCR/issues
Requires-Python: <3.13,>=3.9
License-File: LICENCE
Requires-Dist: shapely
Requires-Dist: scikit-image
Requires-Dist: six
Requires-Dist: pyclipper
Requires-Dist: numpy
Requires-Dist: opencv-python-headless
Requires-Dist: Pillow
Requires-Dist: pyyaml
Requires-Dist: torch
Requires-Dist: torchvision
Requires-Dist: loguru
Requires-Dist: huggingface_hub
